[
  {
    "description": "    As a user\n    I want to be able to create, remove tasks and dates, and change status of tasks.",
    "keyword": "Feature",
    "name": "Tasks organization",
    "line": 1,
    "id": "tasks-organization",
    "tags": [],
    "uri": "e2e\\features\\sprintgrid.feature",
    "elements": [
      {
        "id": "tasks-organization;assign-statuses",
        "keyword": "Scenario",
        "line": 53,
        "name": "Assign statuses",
        "tags": [
          {
            "name": "@e2e",
            "line": 52
          }
        ],
        "type": "scenario",
        "steps": [
          {
            "keyword": "Before",
            "hidden": true,
            "match": {
              "location": "e2e\\features\\step_definitions\\sprintGridStepDef.js:3"
            },
            "result": {
              "status": "passed",
              "duration": 610000000
            }
          },
          {
            "arguments": [],
            "keyword": "Given ",
            "line": 6,
            "name": "I open sprint-grid web application page",
            "match": {
              "location": "e2e\\features\\step_definitions\\sprintGridStepDef.js:10"
            },
            "result": {
              "status": "passed",
              "duration": 752000000
            }
          },
          {
            "arguments": [],
            "keyword": "Then ",
            "line": 54,
            "name": "A cell has no status on it <status>",
            "result": {
              "status": "undefined"
            }
          },
          {
            "arguments": [],
            "keyword": "When ",
            "line": 55,
            "name": "I click on a cell",
            "result": {
              "status": "undefined"
            }
          },
          {
            "arguments": [],
            "keyword": "Then ",
            "line": 56,
            "name": "I see an empty input field",
            "result": {
              "status": "undefined"
            }
          },
          {
            "arguments": [],
            "keyword": "Then ",
            "line": 57,
            "name": "The placeholder text for input field is 'Set Status'",
            "result": {
              "status": "undefined"
            }
          },
          {
            "arguments": [],
            "keyword": "When ",
            "line": 58,
            "name": "I click on an input field",
            "result": {
              "status": "undefined"
            }
          },
          {
            "arguments": [],
            "keyword": "Then ",
            "line": 59,
            "name": "I see statuses list as 'To Do', 'In Progress', 'In Testing', 'Blocked', 'Done'",
            "result": {
              "status": "undefined"
            }
          },
          {
            "arguments": [],
            "keyword": "When ",
            "line": 60,
            "name": "I select <status> status",
            "result": {
              "status": "undefined"
            }
          },
          {
            "arguments": [],
            "keyword": "Then ",
            "line": 61,
            "name": "I am able set the <status> status in cell",
            "result": {
              "status": "undefined"
            }
          },
          {
            "arguments": [],
            "keyword": "Then ",
            "line": 62,
            "name": "The table collapse",
            "result": {
              "status": "undefined"
            }
          },
          {
            "arguments": [],
            "keyword": "When ",
            "line": 63,
            "name": "I click on a cell with status as <status>",
            "result": {
              "status": "undefined"
            }
          },
          {
            "arguments": [],
            "keyword": "Then ",
            "line": 64,
            "name": "I see input field has value <status>",
            "result": {
              "status": "undefined"
            }
          },
          {
            "arguments": [],
            "keyword": "Then ",
            "line": 65,
            "name": "The placeholder text for input field is 'Change status'",
            "result": {
              "status": "undefined"
            }
          },
          {
            "arguments": [],
            "keyword": "When ",
            "line": 66,
            "name": "I click on an input field <status>",
            "result": {
              "status": "undefined"
            }
          },
          {
            "arguments": [],
            "keyword": "Then ",
            "line": 67,
            "name": "I see statuses list as 'To Do', 'In Progress', 'In Testing', 'Blocked', 'Done'",
            "result": {
              "status": "undefined"
            }
          },
          {
            "arguments": [],
            "keyword": "When ",
            "line": 68,
            "name": "I enter \"random\" text in the input field",
            "result": {
              "status": "undefined"
            }
          },
          {
            "arguments": [
              {
                "rows": [
                  {
                    "cells": [
                      "status"
                    ]
                  },
                  {
                    "cells": [
                      "To Do"
                    ]
                  },
                  {
                    "cells": [
                      "In Progress"
                    ]
                  },
                  {
                    "cells": [
                      "In Testing"
                    ]
                  },
                  {
                    "cells": [
                      "Blocked"
                    ]
                  },
                  {
                    "cells": [
                      "Done"
                    ]
                  }
                ]
              }
            ],
            "keyword": "Then ",
            "line": 69,
            "name": "The status <status> is not changed",
            "result": {
              "status": "undefined"
            }
          }
        ]
      }
    ]
  }
]